deploy/create_venv.py
deploy/delete_venv.py
galaxy_py_misc-0.0.2.dist-info/AUTHORS
galaxy_py_misc-0.0.2.dist-info/COPYING.md
galaxy_py_misc-0.0.2.dist-info/LICENSE.txt
galaxy_py_misc-0.0.2.dist-info/METADATA
galaxy_py_misc-0.0.2.dist-info/WHEEL
galaxy_py_misc-0.0.2.dist-info/RECORD
