Metadata-Version: 2.3
Name: galaxy-py-misc
Version: 0.0.2
Summary: Python Miscellaneous for the Galaxy Project
License: Apache-2.0
Keywords: galaxy,galaxy-misc
Author: Bastien Saltel
Author-email: bastien.saltel@gmail.com
Maintainer: Bastien Saltel
Maintainer-email: bastien.saltel@gmail.com
Requires-Python: >=3.10,<4.0
Classifier: Development Status :: 3 - Alpha
Classifier: Programming Language :: Python :: 3
Classifier: Operating System :: OS Independent
Requires-Dist: virtualenv
Requires-Dist: virtualenv-api
Project-URL: Changelog, https://github.com/bsaltel/galaxy-py-misc/blob/main/CHANGELOG.md
Project-URL: Documentation, https://github.com/bsaltel/galaxy-py-misc
Project-URL: Homepage, https://github.com/bsaltel/galaxy-py-misc
Project-URL: Issues, https://github.com/bsaltel/galaxy-py-misc/issues
Project-URL: Repository, https://github.com/bsaltel/galaxy-py-misc.git
